esnb/__init__.py
esnb/core/CaseExperiment.py
esnb/core/CaseExperiment2.py
esnb/core/CaseGroup.py
esnb/core/CaseGroup2.py
esnb/core/NotebookDiagnostic.py
esnb/core/RequestedVariable.py
esnb/core/VirtualDataset.py
esnb/core/__init__.py
esnb/core/esnb_datastore.py
esnb/core/html.py
esnb/core/mdtf.py
esnb/core/util.py
esnb/core/util2.py
esnb/core/util_case.py
esnb/core/util_catalog.py
esnb/core/util_dask.py
esnb/core/util_mdtf.py
esnb/core/util_xr.py
esnb/data/ESM4_ctrl.csv.gz
esnb/data/ESM4_ctrl.json
esnb/data/ESM4_futr.csv.gz
esnb/data/ESM4_futr.json
esnb/data/ESM4_hist.csv.gz
esnb/data/ESM4_hist.json
esnb/data/README.md
esnb/data/blank_catalog.csv
esnb/data/blank_catalog.json
esnb/data/input_timeslice_test.yml
esnb/data/intake-uda-cmip.csv.gz
esnb/data/intake-uda-cmip.json
esnb/data/settings.jsonc
esnb/data/test_catalog_1.csv.gz
esnb/datasources/__init__.py
esnb/engine/__init__.py
esnb/nbtools/__init__.py
esnb/nbtools/xr_stats.py
esnb/sites/__init__.py
esnb/sites/gfdl.py
esnb/templates/MOC_rho-space.ipynb
esnb/templates/MOC_z-space.ipynb
esnb/templates/basic.ipynb
esnb/templates/enso.ipynb
esnb/templates/mdtf.ipynb
esnb/templates/oni_nino34.ipynb
esnb/templates/pangeo.ipynb
esnb/templates/sst_bias.ipynb
esnb-0.9.0.data/scripts/nbinit
esnb-0.9.0.dist-info/METADATA
esnb-0.9.0.dist-info/WHEEL
esnb-0.9.0.dist-info/top_level.txt
esnb-0.9.0.dist-info/RECORD
