Metadata-Version: 2.4
Name: esnb
Version: 0.9.0
Summary: Earth Science Notebook Tools for Climate and Weather Model Analysis
Author-email: John Krasting <john.krasting@noaa.gov>
Project-URL: homepage, https://github.com/jkrasting/esnb
Project-URL: documentation, https://esnb.readthedocs.io
Project-URL: repository, https://github.com/jkrasting/esnb
Keywords: model,analysis
Classifier: Development Status :: 3 - Alpha
Classifier: Intended Audience :: Science/Research
Classifier: Topic :: Scientific/Engineering
Classifier: License :: Public Domain
Classifier: Programming Language :: Python :: 3.11
Classifier: Programming Language :: Python :: 3.12
Requires-Python: >=3.11
Requires-Dist: aiohttp
Requires-Dist: dask
Requires-Dist: dask-jobqueue
Requires-Dist: importlib_metadata<5.0.0
Requires-Dist: importlib-resources
Requires-Dist: intake
Requires-Dist: intake_esm
Requires-Dist: jupyter-client
Requires-Dist: matplotlib
Requires-Dist: momgrid
Requires-Dist: nbclient
Requires-Dist: nbconvert
Requires-Dist: pandas
Requires-Dist: pytest
Requires-Dist: pyyaml
Requires-Dist: xarray
Provides-Extra: test
Requires-Dist: pytest; extra == "test"
